nonebot_plugin_checkbpm/__init__.py
nonebot_plugin_checkbpm-1.0.7.dist-info/LICENSE
nonebot_plugin_checkbpm-1.0.7.dist-info/METADATA
nonebot_plugin_checkbpm-1.0.7.dist-info/WHEEL
nonebot_plugin_checkbpm-1.0.7.dist-info/top_level.txt
nonebot_plugin_checkbpm-1.0.7.dist-info/RECORD
