Metadata-Version: 2.1
Name: nonebot-plugin-checkbpm
Version: 1.0.7
Summary: 基于Librosa的音频文件BPM计算器 通过上传到群文件方式计算音频文件的bpm值（beat per minute）
Author: Ant1
Author-email: glz15757339816@gmail.com
Maintainer-email: Ant1 <glz15757339816@gmail.com>
License: MIT License
Project-URL: homepage, https://github.com/Ant1816/nonebot-plugin-checkbpm
Project-URL: documentation, https://github.com/Ant1816/nonebot-plugin-checkbpm/blob/master/README.md
Project-URL: repository, https://github.com/Ant1816/nonebot-plugin-checkbpm
Project-URL: changelog, https://github.com/Ant1816/nonebot-plugin-checkbpm/commits/master/
Keywords: nonebot2,bpm,music
Classifier: License :: OSI Approved :: MIT License
Classifier: Development Status :: 5 - Production/Stable
Classifier: Programming Language :: Python :: 3.12
Requires-Python: >=3.9
License-File: LICENSE
Requires-Dist: nonebot2>=2.3.1
Requires-Dist: nonebot-adapter-onebot>=2.1.0
Requires-Dist: nonebot_plugin_localstore>=0.7.1
Requires-Dist: librosa>=0.9.1
Requires-Dist: numpy>=2.0.2
Requires-Dist: httpx>=0.27.0
Provides-Extra: test
